// access flags 0x31
public final class testData/cases/whenString/TestKt {

  // compiled from: test.kt


  // access flags 0x108A
  private static transient synthetic [I __$hits$__

  // access flags 0x108A
  private static transient synthetic Ljava/lang/Object; __$classData$__

  // access flags 0x19
  public final static foo(Ljava/lang/String;)V
    // annotable parameter count: 1 (invisible)
    @Lorg/jetbrains/annotations/NotNull;() // invisible, parameter 0
    GETSTATIC testData/cases/whenString/TestKt.__$hits$__ : [I
    IFNONNULL L0
    LDC "testData.cases.whenString.TestKt"
    INVOKESTATIC com/intellij/rt/coverage/instrumentation/CoverageRuntime.getHitsMask (Ljava/lang/String;)[I
    PUTSTATIC testData/cases/whenString/TestKt.__$hits$__ : [I
   L0
    GETSTATIC testData/cases/whenString/TestKt.__$hits$__ : [I
    ASTORE 1
    GETSTATIC testData/cases/whenString/TestKt.__$classData$__ : Ljava/lang/Object;
    IFNONNULL L1
    LDC "testData.cases.whenString.TestKt"
    INVOKESTATIC com/intellij/rt/coverage/instrumentation/CoverageRuntime.loadClassData (Ljava/lang/String;)Ljava/lang/Object;
    PUTSTATIC testData/cases/whenString/TestKt.__$classData$__ : Ljava/lang/Object;
   L1
    GETSTATIC testData/cases/whenString/TestKt.__$classData$__ : Ljava/lang/Object;
    ASTORE 2
   L2
    ALOAD 0
    LDC "x"
    INVOKESTATIC kotlin/jvm/internal/Intrinsics.checkNotNullParameter (Ljava/lang/Object;Ljava/lang/String;)V
   L3
    LINENUMBER 21 L3
    ALOAD 1
    ICONST_0
    DUP2
    IALOAD
    ICONST_1
    IADD
    IASTORE
    ALOAD 2
    BIPUSH 21
    INVOKESTATIC com/intellij/rt/coverage/instrumentation/CoverageRuntime.traceLine (Ljava/lang/Object;I)V
    ALOAD 0
    ASTORE 3
    ALOAD 3
    INVOKEVIRTUAL java/lang/String.hashCode ()I
    GOTO L4
   L5
    ALOAD 1
    ICONST_4
    DUP2
    IALOAD
    ICONST_1
    IADD
    IASTORE
    GOTO L6
   L7
    ALOAD 1
    ICONST_3
    DUP2
    IALOAD
    ICONST_1
    IADD
    IASTORE
    GOTO L8
   L9
    ALOAD 1
    ICONST_2
    DUP2
    IALOAD
    ICONST_1
    IADD
    IASTORE
    GOTO L10
   L11
    ALOAD 1
    ICONST_1
    DUP2
    IALOAD
    ICONST_1
    IADD
    IASTORE
    GOTO L12
   L4
    TABLESWITCH
      97: L5
      98: L7
      99: L9
      default: L11
   L6
   FRAME APPEND [[I java/lang/Object java/lang/String]
    ALOAD 3
    LDC "a"
    INVOKEVIRTUAL java/lang/String.equals (Ljava/lang/Object;)Z
    IFNE L13
    GOTO L14
   L13
    GOTO L15
   L14
    GOTO L12
   L8
   FRAME SAME
    ALOAD 3
    LDC "b"
    INVOKEVIRTUAL java/lang/String.equals (Ljava/lang/Object;)Z
    IFNE L16
    GOTO L17
   L16
    GOTO L15
   L17
    GOTO L12
   L10
   FRAME SAME
    ALOAD 3
    LDC "c"
    INVOKEVIRTUAL java/lang/String.equals (Ljava/lang/Object;)Z
    IFNE L18
    GOTO L19
   L18
    GOTO L20
   L19
    GOTO L12
   L15
    LINENUMBER 22 L15
    ALOAD 1
    BIPUSH 11
    DUP2
    IALOAD
    ICONST_1
    IADD
    IASTORE
    ALOAD 2
    BIPUSH 22
    INVOKESTATIC com/intellij/rt/coverage/instrumentation/CoverageRuntime.traceLine (Ljava/lang/Object;I)V
   L21
   FRAME SAME
    ICONST_5
    ISTORE 4
    GETSTATIC java/lang/System.out : Ljava/io/PrintStream;
    ILOAD 4
    INVOKEVIRTUAL java/io/PrintStream.println (I)V
    GOTO L22
   L20
    LINENUMBER 23 L20
    ALOAD 1
    BIPUSH 12
    DUP2
    IALOAD
    ICONST_1
    IADD
    IASTORE
    ALOAD 2
    BIPUSH 23
    INVOKESTATIC com/intellij/rt/coverage/instrumentation/CoverageRuntime.traceLine (Ljava/lang/Object;I)V
   L23
   FRAME SAME
    BIPUSH 6
    ISTORE 4
    GETSTATIC java/lang/System.out : Ljava/io/PrintStream;
    ILOAD 4
    INVOKEVIRTUAL java/io/PrintStream.println (I)V
    GOTO L22
   L12
    LINENUMBER 24 L12
    ALOAD 1
    BIPUSH 13
    DUP2
    IALOAD
    ICONST_1
    IADD
    IASTORE
    ALOAD 2
    BIPUSH 24
    INVOKESTATIC com/intellij/rt/coverage/instrumentation/CoverageRuntime.traceLine (Ljava/lang/Object;I)V
   L24
   FRAME SAME
    BIPUSH 7
    ISTORE 4
    GETSTATIC java/lang/System.out : Ljava/io/PrintStream;
    ILOAD 4
    INVOKEVIRTUAL java/io/PrintStream.println (I)V
   L22
    LINENUMBER 25 L22
   FRAME APPEND [I]
    RETURN
   L25
    LOCALVARIABLE x Ljava/lang/String; L2 L25 0
    LOCALVARIABLE __$coverage_local$__ [I L0 L25 1
    LOCALVARIABLE __$coverage_local$__ Ljava/lang/Object; L0 L25 2
    MAXSTACK = 5
    MAXLOCALS = 5

  // access flags 0x19
  public final static foo2(Ljava/lang/String;)V
    // annotable parameter count: 1 (invisible)
    @Lorg/jetbrains/annotations/Nullable;() // invisible, parameter 0
    GETSTATIC testData/cases/whenString/TestKt.__$hits$__ : [I
    IFNONNULL L0
    LDC "testData.cases.whenString.TestKt"
    INVOKESTATIC com/intellij/rt/coverage/instrumentation/CoverageRuntime.getHitsMask (Ljava/lang/String;)[I
    PUTSTATIC testData/cases/whenString/TestKt.__$hits$__ : [I
   L0
    GETSTATIC testData/cases/whenString/TestKt.__$hits$__ : [I
    ASTORE 1
    GETSTATIC testData/cases/whenString/TestKt.__$classData$__ : Ljava/lang/Object;
    IFNONNULL L1
    LDC "testData.cases.whenString.TestKt"
    INVOKESTATIC com/intellij/rt/coverage/instrumentation/CoverageRuntime.loadClassData (Ljava/lang/String;)Ljava/lang/Object;
    PUTSTATIC testData/cases/whenString/TestKt.__$classData$__ : Ljava/lang/Object;
   L1
    GETSTATIC testData/cases/whenString/TestKt.__$classData$__ : Ljava/lang/Object;
    ASTORE 2
   L2
    LINENUMBER 28 L2
    ALOAD 1
    BIPUSH 15
    DUP2
    IALOAD
    ICONST_1
    IADD
    IASTORE
    ALOAD 2
    BIPUSH 28
    INVOKESTATIC com/intellij/rt/coverage/instrumentation/CoverageRuntime.traceLine (Ljava/lang/Object;I)V
    ALOAD 0
    ASTORE 3
    ALOAD 3
    IFNULL L3
    GOTO L4
   L3
    GOTO L5
   L4
    ALOAD 3
    INVOKEVIRTUAL java/lang/String.hashCode ()I
    GOTO L6
   L7
    ALOAD 1
    BIPUSH 21
    DUP2
    IALOAD
    ICONST_1
    IADD
    IASTORE
    GOTO L8
   L9
    ALOAD 1
    BIPUSH 20
    DUP2
    IALOAD
    ICONST_1
    IADD
    IASTORE
    GOTO L10
   L11
    ALOAD 1
    BIPUSH 19
    DUP2
    IALOAD
    ICONST_1
    IADD
    IASTORE
    GOTO L12
   L13
    ALOAD 1
    BIPUSH 18
    DUP2
    IALOAD
    ICONST_1
    IADD
    IASTORE
    GOTO L5
   L6
    TABLESWITCH
      97: L7
      98: L9
      99: L11
      default: L13
   L8
   FRAME APPEND [[I java/lang/Object java/lang/String]
    ALOAD 3
    LDC "a"
    INVOKEVIRTUAL java/lang/String.equals (Ljava/lang/Object;)Z
    IFNE L14
    GOTO L15
   L14
    GOTO L16
   L15
    GOTO L5
   L10
   FRAME SAME
    ALOAD 3
    LDC "b"
    INVOKEVIRTUAL java/lang/String.equals (Ljava/lang/Object;)Z
    IFNE L17
    GOTO L18
   L17
    GOTO L16
   L18
    GOTO L5
   L12
   FRAME SAME
    ALOAD 3
    LDC "c"
    INVOKEVIRTUAL java/lang/String.equals (Ljava/lang/Object;)Z
    IFNE L19
    GOTO L20
   L19
    GOTO L21
   L20
    GOTO L5
   L16
    LINENUMBER 29 L16
    ALOAD 1
    BIPUSH 28
    DUP2
    IALOAD
    ICONST_1
    IADD
    IASTORE
    ALOAD 2
    BIPUSH 29
    INVOKESTATIC com/intellij/rt/coverage/instrumentation/CoverageRuntime.traceLine (Ljava/lang/Object;I)V
   L22
   FRAME SAME
    ICONST_5
    ISTORE 4
    GETSTATIC java/lang/System.out : Ljava/io/PrintStream;
    ILOAD 4
    INVOKEVIRTUAL java/io/PrintStream.println (I)V
    GOTO L23
   L21
    LINENUMBER 30 L21
    ALOAD 1
    BIPUSH 29
    DUP2
    IALOAD
    ICONST_1
    IADD
    IASTORE
    ALOAD 2
    BIPUSH 30
    INVOKESTATIC com/intellij/rt/coverage/instrumentation/CoverageRuntime.traceLine (Ljava/lang/Object;I)V
   L24
   FRAME SAME
    BIPUSH 6
    ISTORE 4
    GETSTATIC java/lang/System.out : Ljava/io/PrintStream;
    ILOAD 4
    INVOKEVIRTUAL java/io/PrintStream.println (I)V
    GOTO L23
   L5
    LINENUMBER 31 L5
    ALOAD 1
    BIPUSH 30
    DUP2
    IALOAD
    ICONST_1
    IADD
    IASTORE
    ALOAD 2
    BIPUSH 31
    INVOKESTATIC com/intellij/rt/coverage/instrumentation/CoverageRuntime.traceLine (Ljava/lang/Object;I)V
   L25
   FRAME SAME
    BIPUSH 7
    ISTORE 4
    GETSTATIC java/lang/System.out : Ljava/io/PrintStream;
    ILOAD 4
    INVOKEVIRTUAL java/io/PrintStream.println (I)V
   L23
    LINENUMBER 32 L23
   FRAME APPEND [I]
    RETURN
   L26
    LOCALVARIABLE x Ljava/lang/String; L2 L26 0
    LOCALVARIABLE __$coverage_local$__ [I L0 L26 1
    LOCALVARIABLE __$coverage_local$__ Ljava/lang/Object; L0 L26 2
    MAXSTACK = 5
    MAXLOCALS = 5

  // access flags 0x19
  public final static foo3(Ljava/lang/String;)V
    // annotable parameter count: 1 (invisible)
    @Lorg/jetbrains/annotations/NotNull;() // invisible, parameter 0
    GETSTATIC testData/cases/whenString/TestKt.__$hits$__ : [I
    IFNONNULL L0
    LDC "testData.cases.whenString.TestKt"
    INVOKESTATIC com/intellij/rt/coverage/instrumentation/CoverageRuntime.getHitsMask (Ljava/lang/String;)[I
    PUTSTATIC testData/cases/whenString/TestKt.__$hits$__ : [I
   L0
    GETSTATIC testData/cases/whenString/TestKt.__$hits$__ : [I
    ASTORE 1
    GETSTATIC testData/cases/whenString/TestKt.__$classData$__ : Ljava/lang/Object;
    IFNONNULL L1
    LDC "testData.cases.whenString.TestKt"
    INVOKESTATIC com/intellij/rt/coverage/instrumentation/CoverageRuntime.loadClassData (Ljava/lang/String;)Ljava/lang/Object;
    PUTSTATIC testData/cases/whenString/TestKt.__$classData$__ : Ljava/lang/Object;
   L1
    GETSTATIC testData/cases/whenString/TestKt.__$classData$__ : Ljava/lang/Object;
    ASTORE 2
   L2
    ALOAD 0
    LDC "x"
    INVOKESTATIC kotlin/jvm/internal/Intrinsics.checkNotNullParameter (Ljava/lang/Object;Ljava/lang/String;)V
   L3
    LINENUMBER 35 L3
    ALOAD 1
    BIPUSH 32
    DUP2
    IALOAD
    ICONST_1
    IADD
    IASTORE
    ALOAD 2
    BIPUSH 35
    INVOKESTATIC com/intellij/rt/coverage/instrumentation/CoverageRuntime.traceLine (Ljava/lang/Object;I)V
    ALOAD 0
    ASTORE 3
    ALOAD 3
    INVOKEVIRTUAL java/lang/String.hashCode ()I
    GOTO L4
   L5
    ALOAD 1
    BIPUSH 36
    DUP2
    IALOAD
    ICONST_1
    IADD
    IASTORE
    GOTO L6
   L7
    ALOAD 1
    BIPUSH 35
    DUP2
    IALOAD
    ICONST_1
    IADD
    IASTORE
    GOTO L8
   L9
    ALOAD 1
    BIPUSH 34
    DUP2
    IALOAD
    ICONST_1
    IADD
    IASTORE
    GOTO L10
   L11
    ALOAD 1
    BIPUSH 33
    DUP2
    IALOAD
    ICONST_1
    IADD
    IASTORE
    GOTO L12
   L4
    TABLESWITCH
      97: L5
      98: L7
      99: L9
      default: L11
   L6
   FRAME APPEND [[I java/lang/Object java/lang/String]
    ALOAD 3
    LDC "a"
    INVOKEVIRTUAL java/lang/String.equals (Ljava/lang/Object;)Z
    IFNE L13
    GOTO L14
   L13
    GOTO L15
   L14
    GOTO L12
   L8
   FRAME SAME
    ALOAD 3
    LDC "b"
    INVOKEVIRTUAL java/lang/String.equals (Ljava/lang/Object;)Z
    IFNE L16
    GOTO L17
   L16
    GOTO L15
   L17
    GOTO L12
   L10
   FRAME SAME
    ALOAD 3
    LDC "c"
    INVOKEVIRTUAL java/lang/String.equals (Ljava/lang/Object;)Z
    IFEQ L18
    GOTO L19
   L18
    GOTO L12
   L19
    LINENUMBER 36 L19
    ALOAD 1
    BIPUSH 43
    DUP2
    IALOAD
    ICONST_1
    IADD
    IASTORE
    ALOAD 2
    BIPUSH 36
    INVOKESTATIC com/intellij/rt/coverage/instrumentation/CoverageRuntime.traceLine (Ljava/lang/Object;I)V
    BIPUSH 6
    ISTORE 4
    GETSTATIC java/lang/System.out : Ljava/io/PrintStream;
    ILOAD 4
    INVOKEVIRTUAL java/io/PrintStream.println (I)V
    GOTO L20
   L15
    LINENUMBER 37 L15
    ALOAD 1
    BIPUSH 44
    DUP2
    IALOAD
    ICONST_1
    IADD
    IASTORE
    ALOAD 2
    BIPUSH 37
    INVOKESTATIC com/intellij/rt/coverage/instrumentation/CoverageRuntime.traceLine (Ljava/lang/Object;I)V
   L21
   FRAME SAME
    ICONST_5
    ISTORE 4
    GETSTATIC java/lang/System.out : Ljava/io/PrintStream;
    ILOAD 4
    INVOKEVIRTUAL java/io/PrintStream.println (I)V
    GOTO L20
   L12
    LINENUMBER 38 L12
    ALOAD 1
    BIPUSH 45
    DUP2
    IALOAD
    ICONST_1
    IADD
    IASTORE
    ALOAD 2
    BIPUSH 38
    INVOKESTATIC com/intellij/rt/coverage/instrumentation/CoverageRuntime.traceLine (Ljava/lang/Object;I)V
   L22
   FRAME SAME
    BIPUSH 7
    ISTORE 4
    GETSTATIC java/lang/System.out : Ljava/io/PrintStream;
    ILOAD 4
    INVOKEVIRTUAL java/io/PrintStream.println (I)V
   L20
    LINENUMBER 39 L20
   FRAME APPEND [I]
    RETURN
   L23
    LOCALVARIABLE x Ljava/lang/String; L2 L23 0
    LOCALVARIABLE __$coverage_local$__ [I L0 L23 1
    LOCALVARIABLE __$coverage_local$__ Ljava/lang/Object; L0 L23 2
    MAXSTACK = 5
    MAXLOCALS = 5

  // access flags 0x19
  public final static boo(Ljava/lang/String;)V
    // annotable parameter count: 1 (invisible)
    @Lorg/jetbrains/annotations/NotNull;() // invisible, parameter 0
    GETSTATIC testData/cases/whenString/TestKt.__$hits$__ : [I
    IFNONNULL L0
    LDC "testData.cases.whenString.TestKt"
    INVOKESTATIC com/intellij/rt/coverage/instrumentation/CoverageRuntime.getHitsMask (Ljava/lang/String;)[I
    PUTSTATIC testData/cases/whenString/TestKt.__$hits$__ : [I
   L0
    GETSTATIC testData/cases/whenString/TestKt.__$hits$__ : [I
    ASTORE 1
    GETSTATIC testData/cases/whenString/TestKt.__$classData$__ : Ljava/lang/Object;
    IFNONNULL L1
    LDC "testData.cases.whenString.TestKt"
    INVOKESTATIC com/intellij/rt/coverage/instrumentation/CoverageRuntime.loadClassData (Ljava/lang/String;)Ljava/lang/Object;
    PUTSTATIC testData/cases/whenString/TestKt.__$classData$__ : Ljava/lang/Object;
   L1
    GETSTATIC testData/cases/whenString/TestKt.__$classData$__ : Ljava/lang/Object;
    ASTORE 2
   L2
    ALOAD 0
    LDC "x"
    INVOKESTATIC kotlin/jvm/internal/Intrinsics.checkNotNullParameter (Ljava/lang/Object;Ljava/lang/String;)V
   L3
    LINENUMBER 42 L3
    ALOAD 1
    BIPUSH 47
    DUP2
    IALOAD
    ICONST_1
    IADD
    IASTORE
    ALOAD 2
    BIPUSH 42
    INVOKESTATIC com/intellij/rt/coverage/instrumentation/CoverageRuntime.traceLine (Ljava/lang/Object;I)V
    ALOAD 0
    ASTORE 3
    ALOAD 3
    INVOKEVIRTUAL java/lang/String.hashCode ()I
    GOTO L4
   L5
    ALOAD 1
    BIPUSH 53
    DUP2
    IALOAD
    ICONST_1
    IADD
    IASTORE
    GOTO L6
   L7
    ALOAD 1
    BIPUSH 52
    DUP2
    IALOAD
    ICONST_1
    IADD
    IASTORE
    GOTO L8
   L9
    ALOAD 1
    BIPUSH 51
    DUP2
    IALOAD
    ICONST_1
    IADD
    IASTORE
    GOTO L10
   L11
    ALOAD 1
    BIPUSH 50
    DUP2
    IALOAD
    ICONST_1
    IADD
    IASTORE
    GOTO L12
   L13
    ALOAD 1
    BIPUSH 49
    DUP2
    IALOAD
    ICONST_1
    IADD
    IASTORE
    GOTO L14
   L15
    ALOAD 1
    BIPUSH 48
    DUP2
    IALOAD
    ICONST_1
    IADD
    IASTORE
    GOTO L16
   L4
    LOOKUPSWITCH
      99: L5
      100: L7
      101: L9
      102: L11
      2112: L13
      default: L15
   L14
   FRAME APPEND [[I java/lang/Object java/lang/String]
    ALOAD 3
    LDC "Aa"
    INVOKEVIRTUAL java/lang/String.equals (Ljava/lang/Object;)Z
    IFNE L17
    GOTO L18
   L17
    ALOAD 1
    BIPUSH 54
    DUP2
    IALOAD
    ICONST_1
    IADD
    IASTORE
    GOTO L19
   L18
    ALOAD 1
    BIPUSH 55
    DUP2
    IALOAD
    ICONST_1
    IADD
    IASTORE
    ALOAD 3
    LDC "BB"
    INVOKEVIRTUAL java/lang/String.equals (Ljava/lang/Object;)Z
    IFNE L20
    GOTO L21
   L20
    GOTO L19
   L21
    GOTO L16
   L6
   FRAME SAME
    ALOAD 3
    LDC "c"
    INVOKEVIRTUAL java/lang/String.equals (Ljava/lang/Object;)Z
    IFNE L22
    GOTO L23
   L22
    GOTO L24
   L23
    GOTO L16
   L8
   FRAME SAME
    ALOAD 3
    LDC "d"
    INVOKEVIRTUAL java/lang/String.equals (Ljava/lang/Object;)Z
    IFNE L25
    GOTO L26
   L25
    GOTO L27
   L26
    GOTO L16
   L10
   FRAME SAME
    ALOAD 3
    LDC "e"
    INVOKEVIRTUAL java/lang/String.equals (Ljava/lang/Object;)Z
    IFNE L28
    GOTO L29
   L28
    GOTO L30
   L29
    GOTO L16
   L12
   FRAME SAME
    ALOAD 3
    LDC "f"
    INVOKEVIRTUAL java/lang/String.equals (Ljava/lang/Object;)Z
    IFNE L31
    GOTO L32
   L31
    GOTO L33
   L32
    GOTO L16
   L19
    LINENUMBER 43 L19
    ALOAD 1
    BIPUSH 66
    DUP2
    IALOAD
    ICONST_1
    IADD
    IASTORE
    ALOAD 2
    BIPUSH 43
    INVOKESTATIC com/intellij/rt/coverage/instrumentation/CoverageRuntime.traceLine (Ljava/lang/Object;I)V
   L34
   FRAME SAME
    ICONST_5
    ISTORE 4
    GETSTATIC java/lang/System.out : Ljava/io/PrintStream;
    ILOAD 4
    INVOKEVIRTUAL java/io/PrintStream.println (I)V
    GOTO L35
   L24
    LINENUMBER 44 L24
    ALOAD 1
    BIPUSH 67
    DUP2
    IALOAD
    ICONST_1
    IADD
    IASTORE
    ALOAD 2
    BIPUSH 44
    INVOKESTATIC com/intellij/rt/coverage/instrumentation/CoverageRuntime.traceLine (Ljava/lang/Object;I)V
   L36
   FRAME SAME
    BIPUSH 6
    ISTORE 4
    GETSTATIC java/lang/System.out : Ljava/io/PrintStream;
    ILOAD 4
    INVOKEVIRTUAL java/io/PrintStream.println (I)V
    GOTO L35
   L27
    LINENUMBER 45 L27
    ALOAD 1
    BIPUSH 68
    DUP2
    IALOAD
    ICONST_1
    IADD
    IASTORE
    ALOAD 2
    BIPUSH 45
    INVOKESTATIC com/intellij/rt/coverage/instrumentation/CoverageRuntime.traceLine (Ljava/lang/Object;I)V
   L37
   FRAME SAME
    BIPUSH 7
    ISTORE 4
    GETSTATIC java/lang/System.out : Ljava/io/PrintStream;
    ILOAD 4
    INVOKEVIRTUAL java/io/PrintStream.println (I)V
    GOTO L35
   L30
    LINENUMBER 46 L30
    ALOAD 1
    BIPUSH 69
    DUP2
    IALOAD
    ICONST_1
    IADD
    IASTORE
    ALOAD 2
    BIPUSH 46
    INVOKESTATIC com/intellij/rt/coverage/instrumentation/CoverageRuntime.traceLine (Ljava/lang/Object;I)V
   L38
   FRAME SAME
    BIPUSH 8
    ISTORE 4
    GETSTATIC java/lang/System.out : Ljava/io/PrintStream;
    ILOAD 4
    INVOKEVIRTUAL java/io/PrintStream.println (I)V
    GOTO L35
   L33
    LINENUMBER 47 L33
    ALOAD 1
    BIPUSH 70
    DUP2
    IALOAD
    ICONST_1
    IADD
    IASTORE
    ALOAD 2
    BIPUSH 47
    INVOKESTATIC com/intellij/rt/coverage/instrumentation/CoverageRuntime.traceLine (Ljava/lang/Object;I)V
   L39
   FRAME SAME
    BIPUSH 9
    ISTORE 4
    GETSTATIC java/lang/System.out : Ljava/io/PrintStream;
    ILOAD 4
    INVOKEVIRTUAL java/io/PrintStream.println (I)V
    GOTO L35
   L16
    LINENUMBER 48 L16
    ALOAD 1
    BIPUSH 71
    DUP2
    IALOAD
    ICONST_1
    IADD
    IASTORE
    ALOAD 2
    BIPUSH 48
    INVOKESTATIC com/intellij/rt/coverage/instrumentation/CoverageRuntime.traceLine (Ljava/lang/Object;I)V
   L40
   FRAME SAME
    BIPUSH 10
    ISTORE 4
    GETSTATIC java/lang/System.out : Ljava/io/PrintStream;
    ILOAD 4
    INVOKEVIRTUAL java/io/PrintStream.println (I)V
   L35
    LINENUMBER 49 L35
   FRAME APPEND [I]
    RETURN
   L41
    LOCALVARIABLE x Ljava/lang/String; L2 L41 0
    LOCALVARIABLE __$coverage_local$__ [I L0 L41 1
    LOCALVARIABLE __$coverage_local$__ Ljava/lang/Object; L0 L41 2
    MAXSTACK = 5
    MAXLOCALS = 5

  // access flags 0x19
  public final static boo2(Ljava/lang/String;)V
    // annotable parameter count: 1 (invisible)
    @Lorg/jetbrains/annotations/NotNull;() // invisible, parameter 0
    GETSTATIC testData/cases/whenString/TestKt.__$hits$__ : [I
    IFNONNULL L0
    LDC "testData.cases.whenString.TestKt"
    INVOKESTATIC com/intellij/rt/coverage/instrumentation/CoverageRuntime.getHitsMask (Ljava/lang/String;)[I
    PUTSTATIC testData/cases/whenString/TestKt.__$hits$__ : [I
   L0
    GETSTATIC testData/cases/whenString/TestKt.__$hits$__ : [I
    ASTORE 1
    GETSTATIC testData/cases/whenString/TestKt.__$classData$__ : Ljava/lang/Object;
    IFNONNULL L1
    LDC "testData.cases.whenString.TestKt"
    INVOKESTATIC com/intellij/rt/coverage/instrumentation/CoverageRuntime.loadClassData (Ljava/lang/String;)Ljava/lang/Object;
    PUTSTATIC testData/cases/whenString/TestKt.__$classData$__ : Ljava/lang/Object;
   L1
    GETSTATIC testData/cases/whenString/TestKt.__$classData$__ : Ljava/lang/Object;
    ASTORE 2
   L2
    ALOAD 0
    LDC "x"
    INVOKESTATIC kotlin/jvm/internal/Intrinsics.checkNotNullParameter (Ljava/lang/Object;Ljava/lang/String;)V
   L3
    LINENUMBER 52 L3
    ALOAD 1
    BIPUSH 73
    DUP2
    IALOAD
    ICONST_1
    IADD
    IASTORE
    ALOAD 2
    BIPUSH 52
    INVOKESTATIC com/intellij/rt/coverage/instrumentation/CoverageRuntime.traceLine (Ljava/lang/Object;I)V
    ALOAD 0
    ASTORE 3
    ALOAD 3
    INVOKEVIRTUAL java/lang/String.hashCode ()I
    GOTO L4
   L5
    ALOAD 1
    BIPUSH 79
    DUP2
    IALOAD
    ICONST_1
    IADD
    IASTORE
    GOTO L6
   L7
    ALOAD 1
    BIPUSH 78
    DUP2
    IALOAD
    ICONST_1
    IADD
    IASTORE
    GOTO L8
   L9
    ALOAD 1
    BIPUSH 77
    DUP2
    IALOAD
    ICONST_1
    IADD
    IASTORE
    GOTO L10
   L11
    ALOAD 1
    BIPUSH 76
    DUP2
    IALOAD
    ICONST_1
    IADD
    IASTORE
    GOTO L12
   L13
    ALOAD 1
    BIPUSH 75
    DUP2
    IALOAD
    ICONST_1
    IADD
    IASTORE
    GOTO L14
   L15
    ALOAD 1
    BIPUSH 74
    DUP2
    IALOAD
    ICONST_1
    IADD
    IASTORE
    GOTO L16
   L4
    LOOKUPSWITCH
      99: L5
      100: L7
      101: L9
      102: L11
      2112: L13
      default: L15
   L14
   FRAME APPEND [[I java/lang/Object java/lang/String]
    ALOAD 3
    LDC "Aa"
    INVOKEVIRTUAL java/lang/String.equals (Ljava/lang/Object;)Z
    IFNE L17
    GOTO L18
   L17
    ALOAD 1
    BIPUSH 80
    DUP2
    IALOAD
    ICONST_1
    IADD
    IASTORE
    GOTO L19
   L18
    ALOAD 1
    BIPUSH 81
    DUP2
    IALOAD
    ICONST_1
    IADD
    IASTORE
    ALOAD 3
    LDC "BB"
    INVOKEVIRTUAL java/lang/String.equals (Ljava/lang/Object;)Z
    IFNE L20
    GOTO L21
   L20
    GOTO L19
   L21
    GOTO L16
   L6
   FRAME SAME
    ALOAD 3
    LDC "c"
    INVOKEVIRTUAL java/lang/String.equals (Ljava/lang/Object;)Z
    IFNE L22
    GOTO L23
   L22
    GOTO L24
   L23
    GOTO L16
   L8
   FRAME SAME
    ALOAD 3
    LDC "d"
    INVOKEVIRTUAL java/lang/String.equals (Ljava/lang/Object;)Z
    IFNE L25
    GOTO L26
   L25
    GOTO L27
   L26
    GOTO L16
   L10
   FRAME SAME
    ALOAD 3
    LDC "e"
    INVOKEVIRTUAL java/lang/String.equals (Ljava/lang/Object;)Z
    IFNE L28
    GOTO L29
   L28
    GOTO L30
   L29
    GOTO L16
   L12
   FRAME SAME
    ALOAD 3
    LDC "f"
    INVOKEVIRTUAL java/lang/String.equals (Ljava/lang/Object;)Z
    IFNE L31
    GOTO L32
   L31
    GOTO L33
   L32
    GOTO L16
   L19
    LINENUMBER 53 L19
    ALOAD 1
    BIPUSH 92
    DUP2
    IALOAD
    ICONST_1
    IADD
    IASTORE
    ALOAD 2
    BIPUSH 53
    INVOKESTATIC com/intellij/rt/coverage/instrumentation/CoverageRuntime.traceLine (Ljava/lang/Object;I)V
   L34
   FRAME SAME
    ICONST_5
    ISTORE 4
    GETSTATIC java/lang/System.out : Ljava/io/PrintStream;
    ILOAD 4
    INVOKEVIRTUAL java/io/PrintStream.println (I)V
    GOTO L35
   L24
    LINENUMBER 54 L24
    ALOAD 1
    BIPUSH 93
    DUP2
    IALOAD
    ICONST_1
    IADD
    IASTORE
    ALOAD 2
    BIPUSH 54
    INVOKESTATIC com/intellij/rt/coverage/instrumentation/CoverageRuntime.traceLine (Ljava/lang/Object;I)V
   L36
   FRAME SAME
    BIPUSH 6
    ISTORE 4
    GETSTATIC java/lang/System.out : Ljava/io/PrintStream;
    ILOAD 4
    INVOKEVIRTUAL java/io/PrintStream.println (I)V
    GOTO L35
   L27
    LINENUMBER 55 L27
    ALOAD 1
    BIPUSH 94
    DUP2
    IALOAD
    ICONST_1
    IADD
    IASTORE
    ALOAD 2
    BIPUSH 55
    INVOKESTATIC com/intellij/rt/coverage/instrumentation/CoverageRuntime.traceLine (Ljava/lang/Object;I)V
   L37
   FRAME SAME
    BIPUSH 7
    ISTORE 4
    GETSTATIC java/lang/System.out : Ljava/io/PrintStream;
    ILOAD 4
    INVOKEVIRTUAL java/io/PrintStream.println (I)V
    GOTO L35
   L30
    LINENUMBER 56 L30
    ALOAD 1
    BIPUSH 95
    DUP2
    IALOAD
    ICONST_1
    IADD
    IASTORE
    ALOAD 2
    BIPUSH 56
    INVOKESTATIC com/intellij/rt/coverage/instrumentation/CoverageRuntime.traceLine (Ljava/lang/Object;I)V
   L38
   FRAME SAME
    BIPUSH 8
    ISTORE 4
    GETSTATIC java/lang/System.out : Ljava/io/PrintStream;
    ILOAD 4
    INVOKEVIRTUAL java/io/PrintStream.println (I)V
    GOTO L35
   L33
    LINENUMBER 57 L33
    ALOAD 1
    BIPUSH 96
    DUP2
    IALOAD
    ICONST_1
    IADD
    IASTORE
    ALOAD 2
    BIPUSH 57
    INVOKESTATIC com/intellij/rt/coverage/instrumentation/CoverageRuntime.traceLine (Ljava/lang/Object;I)V
   L39
   FRAME SAME
    BIPUSH 9
    ISTORE 4
    GETSTATIC java/lang/System.out : Ljava/io/PrintStream;
    ILOAD 4
    INVOKEVIRTUAL java/io/PrintStream.println (I)V
    GOTO L35
   L16
    LINENUMBER 58 L16
    ALOAD 1
    BIPUSH 97
    DUP2
    IALOAD
    ICONST_1
    IADD
    IASTORE
    ALOAD 2
    BIPUSH 58
    INVOKESTATIC com/intellij/rt/coverage/instrumentation/CoverageRuntime.traceLine (Ljava/lang/Object;I)V
   L40
   FRAME SAME
    BIPUSH 10
    ISTORE 4
    GETSTATIC java/lang/System.out : Ljava/io/PrintStream;
    ILOAD 4
    INVOKEVIRTUAL java/io/PrintStream.println (I)V
   L35
    LINENUMBER 59 L35
   FRAME APPEND [I]
    RETURN
   L41
    LOCALVARIABLE x Ljava/lang/String; L2 L41 0
    LOCALVARIABLE __$coverage_local$__ [I L0 L41 1
    LOCALVARIABLE __$coverage_local$__ Ljava/lang/Object; L0 L41 2
    MAXSTACK = 5
    MAXLOCALS = 5

  // access flags 0x19
  public final static voo(Ljava/lang/String;)V
    // annotable parameter count: 1 (invisible)
    @Lorg/jetbrains/annotations/NotNull;() // invisible, parameter 0
    GETSTATIC testData/cases/whenString/TestKt.__$hits$__ : [I
    IFNONNULL L0
    LDC "testData.cases.whenString.TestKt"
    INVOKESTATIC com/intellij/rt/coverage/instrumentation/CoverageRuntime.getHitsMask (Ljava/lang/String;)[I
    PUTSTATIC testData/cases/whenString/TestKt.__$hits$__ : [I
   L0
    GETSTATIC testData/cases/whenString/TestKt.__$hits$__ : [I
    ASTORE 1
    GETSTATIC testData/cases/whenString/TestKt.__$classData$__ : Ljava/lang/Object;
    IFNONNULL L1
    LDC "testData.cases.whenString.TestKt"
    INVOKESTATIC com/intellij/rt/coverage/instrumentation/CoverageRuntime.loadClassData (Ljava/lang/String;)Ljava/lang/Object;
    PUTSTATIC testData/cases/whenString/TestKt.__$classData$__ : Ljava/lang/Object;
   L1
    GETSTATIC testData/cases/whenString/TestKt.__$classData$__ : Ljava/lang/Object;
    ASTORE 2
   L2
    ALOAD 0
    LDC "x"
    INVOKESTATIC kotlin/jvm/internal/Intrinsics.checkNotNullParameter (Ljava/lang/Object;Ljava/lang/String;)V
   L3
    LINENUMBER 62 L3
    ALOAD 1
    BIPUSH 99
    DUP2
    IALOAD
    ICONST_1
    IADD
    IASTORE
    ALOAD 2
    BIPUSH 62
    INVOKESTATIC com/intellij/rt/coverage/instrumentation/CoverageRuntime.traceLine (Ljava/lang/Object;I)V
    ALOAD 0
    ASTORE 3
   L4
    LINENUMBER 63 L4
    ALOAD 1
    BIPUSH 100
    DUP2
    IALOAD
    ICONST_1
    IADD
    IASTORE
    ALOAD 2
    BIPUSH 63
    INVOKESTATIC com/intellij/rt/coverage/instrumentation/CoverageRuntime.traceLine (Ljava/lang/Object;I)V
    ALOAD 3
    LDC "Aa"
    INVOKESTATIC kotlin/jvm/internal/Intrinsics.areEqual (Ljava/lang/Object;Ljava/lang/Object;)Z
    IFEQ L5
    GOTO L6
   L5
    ALOAD 1
    BIPUSH 101
    DUP2
    IALOAD
    ICONST_1
    IADD
    IASTORE
    GOTO L7
   L6
    ALOAD 1
    BIPUSH 102
    DUP2
    IALOAD
    ICONST_1
    IADD
    IASTORE
    ICONST_1
    GOTO L8
   L7
   FRAME APPEND [[I java/lang/Object java/lang/String]
    ALOAD 3
    LDC "BB"
    INVOKESTATIC kotlin/jvm/internal/Intrinsics.areEqual (Ljava/lang/Object;Ljava/lang/Object;)Z
   L8
   FRAME SAME1 I
    IFEQ L9
    GOTO L10
   L9
    ALOAD 1
    BIPUSH 103
    DUP2
    IALOAD
    ICONST_1
    IADD
    IASTORE
    GOTO L11
   L10
    ALOAD 1
    BIPUSH 104
    DUP2
    IALOAD
    ICONST_1
    IADD
    IASTORE
    ICONST_5
    ISTORE 4
    GETSTATIC java/lang/System.out : Ljava/io/PrintStream;
    ILOAD 4
    INVOKEVIRTUAL java/io/PrintStream.println (I)V
    GOTO L12
   L11
    LINENUMBER 64 L11
    ALOAD 1
    BIPUSH 105
    DUP2
    IALOAD
    ICONST_1
    IADD
    IASTORE
    ALOAD 2
    BIPUSH 64
    INVOKESTATIC com/intellij/rt/coverage/instrumentation/CoverageRuntime.traceLine (Ljava/lang/Object;I)V
   L13
   FRAME SAME
    BIPUSH 10
    ISTORE 4
    GETSTATIC java/lang/System.out : Ljava/io/PrintStream;
    ILOAD 4
    INVOKEVIRTUAL java/io/PrintStream.println (I)V
   L12
    LINENUMBER 65 L12
   FRAME APPEND [I]
    RETURN
   L14
    LOCALVARIABLE x Ljava/lang/String; L2 L14 0
    LOCALVARIABLE __$coverage_local$__ [I L0 L14 1
    LOCALVARIABLE __$coverage_local$__ Ljava/lang/Object; L0 L14 2
    MAXSTACK = 4
    MAXLOCALS = 5

  // access flags 0x19
  public final static main()V
    GETSTATIC testData/cases/whenString/TestKt.__$hits$__ : [I
    IFNONNULL L0
    LDC "testData.cases.whenString.TestKt"
    INVOKESTATIC com/intellij/rt/coverage/instrumentation/CoverageRuntime.getHitsMask (Ljava/lang/String;)[I
    PUTSTATIC testData/cases/whenString/TestKt.__$hits$__ : [I
   L0
    GETSTATIC testData/cases/whenString/TestKt.__$hits$__ : [I
    ASTORE 0
    GETSTATIC testData/cases/whenString/TestKt.__$classData$__ : Ljava/lang/Object;
    IFNONNULL L1
    LDC "testData.cases.whenString.TestKt"
    INVOKESTATIC com/intellij/rt/coverage/instrumentation/CoverageRuntime.loadClassData (Ljava/lang/String;)Ljava/lang/Object;
    PUTSTATIC testData/cases/whenString/TestKt.__$classData$__ : Ljava/lang/Object;
   L1
    GETSTATIC testData/cases/whenString/TestKt.__$classData$__ : Ljava/lang/Object;
    ASTORE 1
   L2
    LINENUMBER 68 L2
    ALOAD 0
    BIPUSH 107
    DUP2
    IALOAD
    ICONST_1
    IADD
    IASTORE
    ALOAD 1
    BIPUSH 68
    INVOKESTATIC com/intellij/rt/coverage/instrumentation/CoverageRuntime.traceLine (Ljava/lang/Object;I)V
    LDC "a"
    INVOKESTATIC testData/cases/whenString/TestKt.foo (Ljava/lang/String;)V
   L3
    LINENUMBER 69 L3
    ALOAD 0
    BIPUSH 108
    DUP2
    IALOAD
    ICONST_1
    IADD
    IASTORE
    ALOAD 1
    BIPUSH 69
    INVOKESTATIC com/intellij/rt/coverage/instrumentation/CoverageRuntime.traceLine (Ljava/lang/Object;I)V
    LDC "b"
    INVOKESTATIC testData/cases/whenString/TestKt.foo (Ljava/lang/String;)V
   L4
    LINENUMBER 70 L4
    ALOAD 0
    BIPUSH 109
    DUP2
    IALOAD
    ICONST_1
    IADD
    IASTORE
    ALOAD 1
    BIPUSH 70
    INVOKESTATIC com/intellij/rt/coverage/instrumentation/CoverageRuntime.traceLine (Ljava/lang/Object;I)V
    LDC "c"
    INVOKESTATIC testData/cases/whenString/TestKt.foo (Ljava/lang/String;)V
   L5
    LINENUMBER 71 L5
    ALOAD 0
    BIPUSH 110
    DUP2
    IALOAD
    ICONST_1
    IADD
    IASTORE
    ALOAD 1
    BIPUSH 71
    INVOKESTATIC com/intellij/rt/coverage/instrumentation/CoverageRuntime.traceLine (Ljava/lang/Object;I)V
    LDC "d"
    INVOKESTATIC testData/cases/whenString/TestKt.foo (Ljava/lang/String;)V
   L6
    LINENUMBER 73 L6
    ALOAD 0
    BIPUSH 111
    DUP2
    IALOAD
    ICONST_1
    IADD
    IASTORE
    ALOAD 1
    BIPUSH 73
    INVOKESTATIC com/intellij/rt/coverage/instrumentation/CoverageRuntime.traceLine (Ljava/lang/Object;I)V
    LDC "a"
    INVOKESTATIC testData/cases/whenString/TestKt.foo2 (Ljava/lang/String;)V
   L7
    LINENUMBER 74 L7
    ALOAD 0
    BIPUSH 112
    DUP2
    IALOAD
    ICONST_1
    IADD
    IASTORE
    ALOAD 1
    BIPUSH 74
    INVOKESTATIC com/intellij/rt/coverage/instrumentation/CoverageRuntime.traceLine (Ljava/lang/Object;I)V
    LDC "b"
    INVOKESTATIC testData/cases/whenString/TestKt.foo2 (Ljava/lang/String;)V
   L8
    LINENUMBER 75 L8
    ALOAD 0
    BIPUSH 113
    DUP2
    IALOAD
    ICONST_1
    IADD
    IASTORE
    ALOAD 1
    BIPUSH 75
    INVOKESTATIC com/intellij/rt/coverage/instrumentation/CoverageRuntime.traceLine (Ljava/lang/Object;I)V
    LDC "c"
    INVOKESTATIC testData/cases/whenString/TestKt.foo2 (Ljava/lang/String;)V
   L9
    LINENUMBER 76 L9
    ALOAD 0
    BIPUSH 114
    DUP2
    IALOAD
    ICONST_1
    IADD
    IASTORE
    ALOAD 1
    BIPUSH 76
    INVOKESTATIC com/intellij/rt/coverage/instrumentation/CoverageRuntime.traceLine (Ljava/lang/Object;I)V
    LDC "d"
    INVOKESTATIC testData/cases/whenString/TestKt.foo2 (Ljava/lang/String;)V
   L10
    LINENUMBER 78 L10
    ALOAD 0
    BIPUSH 115
    DUP2
    IALOAD
    ICONST_1
    IADD
    IASTORE
    ALOAD 1
    BIPUSH 78
    INVOKESTATIC com/intellij/rt/coverage/instrumentation/CoverageRuntime.traceLine (Ljava/lang/Object;I)V
    LDC "a"
    INVOKESTATIC testData/cases/whenString/TestKt.foo3 (Ljava/lang/String;)V
   L11
    LINENUMBER 79 L11
    ALOAD 0
    BIPUSH 116
    DUP2
    IALOAD
    ICONST_1
    IADD
    IASTORE
    ALOAD 1
    BIPUSH 79
    INVOKESTATIC com/intellij/rt/coverage/instrumentation/CoverageRuntime.traceLine (Ljava/lang/Object;I)V
    LDC "b"
    INVOKESTATIC testData/cases/whenString/TestKt.foo3 (Ljava/lang/String;)V
   L12
    LINENUMBER 80 L12
    ALOAD 0
    BIPUSH 117
    DUP2
    IALOAD
    ICONST_1
    IADD
    IASTORE
    ALOAD 1
    BIPUSH 80
    INVOKESTATIC com/intellij/rt/coverage/instrumentation/CoverageRuntime.traceLine (Ljava/lang/Object;I)V
    LDC "c"
    INVOKESTATIC testData/cases/whenString/TestKt.foo3 (Ljava/lang/String;)V
   L13
    LINENUMBER 81 L13
    ALOAD 0
    BIPUSH 118
    DUP2
    IALOAD
    ICONST_1
    IADD
    IASTORE
    ALOAD 1
    BIPUSH 81
    INVOKESTATIC com/intellij/rt/coverage/instrumentation/CoverageRuntime.traceLine (Ljava/lang/Object;I)V
    LDC "d"
    INVOKESTATIC testData/cases/whenString/TestKt.foo3 (Ljava/lang/String;)V
   L14
    LINENUMBER 83 L14
    ALOAD 0
    BIPUSH 119
    DUP2
    IALOAD
    ICONST_1
    IADD
    IASTORE
    ALOAD 1
    BIPUSH 83
    INVOKESTATIC com/intellij/rt/coverage/instrumentation/CoverageRuntime.traceLine (Ljava/lang/Object;I)V
    LDC "Aa"
    INVOKESTATIC testData/cases/whenString/TestKt.boo (Ljava/lang/String;)V
   L15
    LINENUMBER 84 L15
    ALOAD 0
    BIPUSH 120
    DUP2
    IALOAD
    ICONST_1
    IADD
    IASTORE
    ALOAD 1
    BIPUSH 84
    INVOKESTATIC com/intellij/rt/coverage/instrumentation/CoverageRuntime.traceLine (Ljava/lang/Object;I)V
    LDC "BB"
    INVOKESTATIC testData/cases/whenString/TestKt.boo (Ljava/lang/String;)V
   L16
    LINENUMBER 85 L16
    ALOAD 0
    BIPUSH 121
    DUP2
    IALOAD
    ICONST_1
    IADD
    IASTORE
    ALOAD 1
    BIPUSH 85
    INVOKESTATIC com/intellij/rt/coverage/instrumentation/CoverageRuntime.traceLine (Ljava/lang/Object;I)V
    LDC "c"
    INVOKESTATIC testData/cases/whenString/TestKt.boo (Ljava/lang/String;)V
   L17
    LINENUMBER 86 L17
    ALOAD 0
    BIPUSH 122
    DUP2
    IALOAD
    ICONST_1
    IADD
    IASTORE
    ALOAD 1
    BIPUSH 86
    INVOKESTATIC com/intellij/rt/coverage/instrumentation/CoverageRuntime.traceLine (Ljava/lang/Object;I)V
    LDC "d"
    INVOKESTATIC testData/cases/whenString/TestKt.boo (Ljava/lang/String;)V
   L18
    LINENUMBER 87 L18
    ALOAD 0
    BIPUSH 123
    DUP2
    IALOAD
    ICONST_1
    IADD
    IASTORE
    ALOAD 1
    BIPUSH 87
    INVOKESTATIC com/intellij/rt/coverage/instrumentation/CoverageRuntime.traceLine (Ljava/lang/Object;I)V
    LDC "e"
    INVOKESTATIC testData/cases/whenString/TestKt.boo (Ljava/lang/String;)V
   L19
    LINENUMBER 88 L19
    ALOAD 0
    BIPUSH 124
    DUP2
    IALOAD
    ICONST_1
    IADD
    IASTORE
    ALOAD 1
    BIPUSH 88
    INVOKESTATIC com/intellij/rt/coverage/instrumentation/CoverageRuntime.traceLine (Ljava/lang/Object;I)V
    LDC "f"
    INVOKESTATIC testData/cases/whenString/TestKt.boo (Ljava/lang/String;)V
   L20
    LINENUMBER 89 L20
    ALOAD 0
    BIPUSH 125
    DUP2
    IALOAD
    ICONST_1
    IADD
    IASTORE
    ALOAD 1
    BIPUSH 89
    INVOKESTATIC com/intellij/rt/coverage/instrumentation/CoverageRuntime.traceLine (Ljava/lang/Object;I)V
    LDC "g"
    INVOKESTATIC testData/cases/whenString/TestKt.boo (Ljava/lang/String;)V
   L21
    LINENUMBER 91 L21
    ALOAD 0
    BIPUSH 126
    DUP2
    IALOAD
    ICONST_1
    IADD
    IASTORE
    ALOAD 1
    BIPUSH 91
    INVOKESTATIC com/intellij/rt/coverage/instrumentation/CoverageRuntime.traceLine (Ljava/lang/Object;I)V
    LDC "Aa"
    INVOKESTATIC testData/cases/whenString/TestKt.boo2 (Ljava/lang/String;)V
   L22
    LINENUMBER 92 L22
    ALOAD 0
    BIPUSH 127
    DUP2
    IALOAD
    ICONST_1
    IADD
    IASTORE
    ALOAD 1
    BIPUSH 92
    INVOKESTATIC com/intellij/rt/coverage/instrumentation/CoverageRuntime.traceLine (Ljava/lang/Object;I)V
    LDC "c"
    INVOKESTATIC testData/cases/whenString/TestKt.boo2 (Ljava/lang/String;)V
   L23
    LINENUMBER 93 L23
    ALOAD 0
    SIPUSH 128
    DUP2
    IALOAD
    ICONST_1
    IADD
    IASTORE
    ALOAD 1
    BIPUSH 93
    INVOKESTATIC com/intellij/rt/coverage/instrumentation/CoverageRuntime.traceLine (Ljava/lang/Object;I)V
    LDC "d"
    INVOKESTATIC testData/cases/whenString/TestKt.boo2 (Ljava/lang/String;)V
   L24
    LINENUMBER 94 L24
    ALOAD 0
    SIPUSH 129
    DUP2
    IALOAD
    ICONST_1
    IADD
    IASTORE
    ALOAD 1
    BIPUSH 94
    INVOKESTATIC com/intellij/rt/coverage/instrumentation/CoverageRuntime.traceLine (Ljava/lang/Object;I)V
    LDC "e"
    INVOKESTATIC testData/cases/whenString/TestKt.boo2 (Ljava/lang/String;)V
   L25
    LINENUMBER 95 L25
    ALOAD 0
    SIPUSH 130
    DUP2
    IALOAD
    ICONST_1
    IADD
    IASTORE
    ALOAD 1
    BIPUSH 95
    INVOKESTATIC com/intellij/rt/coverage/instrumentation/CoverageRuntime.traceLine (Ljava/lang/Object;I)V
    LDC "f"
    INVOKESTATIC testData/cases/whenString/TestKt.boo2 (Ljava/lang/String;)V
   L26
    LINENUMBER 96 L26
    ALOAD 0
    SIPUSH 131
    DUP2
    IALOAD
    ICONST_1
    IADD
    IASTORE
    ALOAD 1
    BIPUSH 96
    INVOKESTATIC com/intellij/rt/coverage/instrumentation/CoverageRuntime.traceLine (Ljava/lang/Object;I)V
    LDC "g"
    INVOKESTATIC testData/cases/whenString/TestKt.boo2 (Ljava/lang/String;)V
   L27
    LINENUMBER 98 L27
    ALOAD 0
    SIPUSH 132
    DUP2
    IALOAD
    ICONST_1
    IADD
    IASTORE
    ALOAD 1
    BIPUSH 98
    INVOKESTATIC com/intellij/rt/coverage/instrumentation/CoverageRuntime.traceLine (Ljava/lang/Object;I)V
    LDC "Aa"
    INVOKESTATIC testData/cases/whenString/TestKt.voo (Ljava/lang/String;)V
   L28
    LINENUMBER 99 L28
    ALOAD 0
    SIPUSH 133
    DUP2
    IALOAD
    ICONST_1
    IADD
    IASTORE
    ALOAD 1
    BIPUSH 99
    INVOKESTATIC com/intellij/rt/coverage/instrumentation/CoverageRuntime.traceLine (Ljava/lang/Object;I)V
    LDC "BB"
    INVOKESTATIC testData/cases/whenString/TestKt.voo (Ljava/lang/String;)V
   L29
    LINENUMBER 100 L29
    ALOAD 0
    SIPUSH 134
    DUP2
    IALOAD
    ICONST_1
    IADD
    IASTORE
    ALOAD 1
    BIPUSH 100
    INVOKESTATIC com/intellij/rt/coverage/instrumentation/CoverageRuntime.traceLine (Ljava/lang/Object;I)V
    LDC "g"
    INVOKESTATIC testData/cases/whenString/TestKt.voo (Ljava/lang/String;)V
   L30
    LINENUMBER 101 L30
    RETURN
    LOCALVARIABLE __$coverage_local$__ [I L0 L30 0
    LOCALVARIABLE __$coverage_local$__ Ljava/lang/Object; L0 L30 1
    MAXSTACK = 4
    MAXLOCALS = 2

  // access flags 0x1009
  public static synthetic main([Ljava/lang/String;)V
    GETSTATIC testData/cases/whenString/TestKt.__$classData$__ : Ljava/lang/Object;
    IFNONNULL L0
    LDC "testData.cases.whenString.TestKt"
    INVOKESTATIC com/intellij/rt/coverage/instrumentation/CoverageRuntime.loadClassData (Ljava/lang/String;)Ljava/lang/Object;
    PUTSTATIC testData/cases/whenString/TestKt.__$classData$__ : Ljava/lang/Object;
   L0
    GETSTATIC testData/cases/whenString/TestKt.__$classData$__ : Ljava/lang/Object;
    ASTORE 1
   L1
    INVOKESTATIC testData/cases/whenString/TestKt.main ()V
    RETURN
   L2
    LOCALVARIABLE args [Ljava/lang/String; L1 L2 0
    LOCALVARIABLE __$coverage_local$__ Ljava/lang/Object; L0 L2 1
    MAXSTACK = 1
    MAXLOCALS = 2
}
