// access flags 0x31
public final class testData/simple/branches/MyBranchedClass {

  // compiled from: test.kt


  @Landroidx/compose/runtime/internal/StabilityInferred;(parameters=1) // invisible

  // access flags 0x19
  public final static I $stable

  // access flags 0x108A
  private static transient synthetic [Z __$hits$__

  // access flags 0x108A
  private static transient synthetic [Z __$traceMask$__

  // access flags 0x108A
  private static transient synthetic Ljava/lang/Object; __$classData$__

  // access flags 0x1
  public <init>()V
    GETSTATIC testData/simple/branches/MyBranchedClass.__$hits$__ : [Z
    IFNONNULL L0
    LDC "testData.simple.branches.MyBranchedClass"
    INVOKESTATIC com/intellij/rt/coverage/instrumentation/CoverageRuntime.getHitsMask (Ljava/lang/String;)[Z
    PUTSTATIC testData/simple/branches/MyBranchedClass.__$hits$__ : [Z
   L0
    GETSTATIC testData/simple/branches/MyBranchedClass.__$hits$__ : [Z
    ASTORE 1
    GETSTATIC testData/simple/branches/MyBranchedClass.__$traceMask$__ : [Z
    IFNONNULL L1
    LDC "testData.simple.branches.MyBranchedClass"
    INVOKESTATIC com/intellij/rt/coverage/instrumentation/CoverageRuntime.getTraceMask (Ljava/lang/String;)[Z
    PUTSTATIC testData/simple/branches/MyBranchedClass.__$traceMask$__ : [Z
   L1
    GETSTATIC testData/simple/branches/MyBranchedClass.__$traceMask$__ : [Z
    ASTORE 2
    GETSTATIC testData/simple/branches/MyBranchedClass.__$classData$__ : Ljava/lang/Object;
    IFNONNULL L2
    LDC "testData.simple.branches.MyBranchedClass"
    INVOKESTATIC com/intellij/rt/coverage/instrumentation/CoverageRuntime.loadClassData (Ljava/lang/String;)Ljava/lang/Object;
    PUTSTATIC testData/simple/branches/MyBranchedClass.__$classData$__ : Ljava/lang/Object;
   L2
    GETSTATIC testData/simple/branches/MyBranchedClass.__$classData$__ : Ljava/lang/Object;
    ASTORE 3
   L3
    LINENUMBER 22 L3
    ALOAD 1
    ICONST_0
    ICONST_1
    BASTORE
    ALOAD 2
    DUP
    ALOAD 3
    INVOKESTATIC com/intellij/rt/coverage/instrumentation/CoverageRuntime.checkRegister ([ZLjava/lang/Object;)V
    BIPUSH 22
    ICONST_1
    BASTORE
    ALOAD 0
    INVOKESPECIAL java/lang/Object.<init> ()V
    RETURN
   L4
    LOCALVARIABLE this LtestData/simple/branches/MyBranchedClass; L3 L4 0
    LOCALVARIABLE __$coverage_local$__ [Z L0 L4 1
    LOCALVARIABLE __$coverage_local$__ [Z L0 L4 2
    LOCALVARIABLE __$coverage_local$__ Ljava/lang/Object; L0 L4 3
    MAXSTACK = 3
    MAXLOCALS = 4

  // access flags 0x11
  public final foo(I)V
    GETSTATIC testData/simple/branches/MyBranchedClass.__$hits$__ : [Z
    IFNONNULL L0
    LDC "testData.simple.branches.MyBranchedClass"
    INVOKESTATIC com/intellij/rt/coverage/instrumentation/CoverageRuntime.getHitsMask (Ljava/lang/String;)[Z
    PUTSTATIC testData/simple/branches/MyBranchedClass.__$hits$__ : [Z
   L0
    GETSTATIC testData/simple/branches/MyBranchedClass.__$hits$__ : [Z
    ASTORE 2
    GETSTATIC testData/simple/branches/MyBranchedClass.__$traceMask$__ : [Z
    IFNONNULL L1
    LDC "testData.simple.branches.MyBranchedClass"
    INVOKESTATIC com/intellij/rt/coverage/instrumentation/CoverageRuntime.getTraceMask (Ljava/lang/String;)[Z
    PUTSTATIC testData/simple/branches/MyBranchedClass.__$traceMask$__ : [Z
   L1
    GETSTATIC testData/simple/branches/MyBranchedClass.__$traceMask$__ : [Z
    ASTORE 3
    GETSTATIC testData/simple/branches/MyBranchedClass.__$classData$__ : Ljava/lang/Object;
    IFNONNULL L2
    LDC "testData.simple.branches.MyBranchedClass"
    INVOKESTATIC com/intellij/rt/coverage/instrumentation/CoverageRuntime.loadClassData (Ljava/lang/String;)Ljava/lang/Object;
    PUTSTATIC testData/simple/branches/MyBranchedClass.__$classData$__ : Ljava/lang/Object;
   L2
    GETSTATIC testData/simple/branches/MyBranchedClass.__$classData$__ : Ljava/lang/Object;
    ASTORE 4
   L3
    LINENUMBER 24 L3
    ALOAD 2
    ICONST_1
    ICONST_1
    BASTORE
    ALOAD 3
    DUP
    ALOAD 4
    INVOKESTATIC com/intellij/rt/coverage/instrumentation/CoverageRuntime.checkRegister ([ZLjava/lang/Object;)V
    BIPUSH 24
    ICONST_1
    BASTORE
    ILOAD 1
    IFGE L4
    GOTO L5
   L4
    ALOAD 2
    ICONST_2
    ICONST_1
    BASTORE
    GOTO L6
   L5
    ALOAD 2
    ICONST_3
    ICONST_1
    BASTORE
   L7
    LINENUMBER 25 L7
    ALOAD 2
    ICONST_4
    ICONST_1
    BASTORE
    ALOAD 3
    DUP
    ALOAD 4
    INVOKESTATIC com/intellij/rt/coverage/instrumentation/CoverageRuntime.checkRegister ([ZLjava/lang/Object;)V
    BIPUSH 25
    ICONST_1
    BASTORE
    LDC "LE"
    GETSTATIC java/lang/System.out : Ljava/io/PrintStream;
    SWAP
    INVOKEVIRTUAL java/io/PrintStream.println (Ljava/lang/Object;)V
    GOTO L8
   L6
    LINENUMBER 26 L6
    ALOAD 2
    ICONST_5
    ICONST_1
    BASTORE
    ALOAD 3
    DUP
    ALOAD 4
    INVOKESTATIC com/intellij/rt/coverage/instrumentation/CoverageRuntime.checkRegister ([ZLjava/lang/Object;)V
    BIPUSH 26
    ICONST_1
    BASTORE
   L9
   FRAME APPEND [[Z [Z java/lang/Object]
    ILOAD 1
    IFNE L10
    GOTO L11
   L10
    ALOAD 2
    BIPUSH 6
    ICONST_1
    BASTORE
    GOTO L12
   L11
    ALOAD 2
    BIPUSH 7
    ICONST_1
    BASTORE
   L13
    LINENUMBER 27 L13
    ALOAD 2
    BIPUSH 8
    ICONST_1
    BASTORE
    ALOAD 3
    DUP
    ALOAD 4
    INVOKESTATIC com/intellij/rt/coverage/instrumentation/CoverageRuntime.checkRegister ([ZLjava/lang/Object;)V
    BIPUSH 27
    ICONST_1
    BASTORE
    LDC "EQ"
    GETSTATIC java/lang/System.out : Ljava/io/PrintStream;
    SWAP
    INVOKEVIRTUAL java/io/PrintStream.println (Ljava/lang/Object;)V
    GOTO L8
   L12
    LINENUMBER 29 L12
    ALOAD 2
    BIPUSH 9
    ICONST_1
    BASTORE
    ALOAD 3
    DUP
    ALOAD 4
    INVOKESTATIC com/intellij/rt/coverage/instrumentation/CoverageRuntime.checkRegister ([ZLjava/lang/Object;)V
    BIPUSH 29
    ICONST_1
    BASTORE
   L14
   FRAME SAME
    LDC "GE"
    GETSTATIC java/lang/System.out : Ljava/io/PrintStream;
    SWAP
    INVOKEVIRTUAL java/io/PrintStream.println (Ljava/lang/Object;)V
   L8
    LINENUMBER 31 L8
   FRAME SAME
    RETURN
   L15
    LOCALVARIABLE this LtestData/simple/branches/MyBranchedClass; L3 L15 0
    LOCALVARIABLE value I L3 L15 1
    LOCALVARIABLE __$coverage_local$__ [Z L0 L15 2
    LOCALVARIABLE __$coverage_local$__ [Z L0 L15 3
    LOCALVARIABLE __$coverage_local$__ Ljava/lang/Object; L0 L15 4
    MAXSTACK = 3
    MAXLOCALS = 5

  // access flags 0x8
  static <clinit>()V
    GETSTATIC testData/simple/branches/MyBranchedClass.__$traceMask$__ : [Z
    IFNONNULL L0
    LDC "testData.simple.branches.MyBranchedClass"
    INVOKESTATIC com/intellij/rt/coverage/instrumentation/CoverageRuntime.getTraceMask (Ljava/lang/String;)[Z
    PUTSTATIC testData/simple/branches/MyBranchedClass.__$traceMask$__ : [Z
   L0
    GETSTATIC testData/simple/branches/MyBranchedClass.__$traceMask$__ : [Z
    ASTORE 0
    GETSTATIC testData/simple/branches/MyBranchedClass.__$classData$__ : Ljava/lang/Object;
    IFNONNULL L1
    LDC "testData.simple.branches.MyBranchedClass"
    INVOKESTATIC com/intellij/rt/coverage/instrumentation/CoverageRuntime.loadClassData (Ljava/lang/String;)Ljava/lang/Object;
    PUTSTATIC testData/simple/branches/MyBranchedClass.__$classData$__ : Ljava/lang/Object;
   L1
    GETSTATIC testData/simple/branches/MyBranchedClass.__$classData$__ : Ljava/lang/Object;
    ASTORE 1
    RETURN
    LOCALVARIABLE __$coverage_local$__ [Z L0 L0 0
    LOCALVARIABLE __$coverage_local$__ Ljava/lang/Object; L0 L1 1
    MAXSTACK = 1
    MAXLOCALS = 2
}
